cotd_stats_visualiser/__init__.py
cotd_stats_visualiser/__main__.py
cotd_stats_visualiser/const.py
cotd_stats_visualiser/main.py
cotd_stats_visualiser/utils.py
cotd_stats_visualiser-0.0.1a3.dist-info/LICENSE
cotd_stats_visualiser-0.0.1a3.dist-info/METADATA
cotd_stats_visualiser-0.0.1a3.dist-info/WHEEL
cotd_stats_visualiser-0.0.1a3.dist-info/top_level.txt
cotd_stats_visualiser-0.0.1a3.dist-info/RECORD
